LICENSE
README.md
setup.py
CellTasker/__init__.py
CellTasker/cell.py
CellTasker/controller.py
CellTasker/pub.py
CellTasker.egg-info/PKG-INFO
CellTasker.egg-info/SOURCES.txt
CellTasker.egg-info/dependency_links.txt
CellTasker.egg-info/requires.txt
CellTasker.egg-info/top_level.txt