Metadata-Version: 2.1
Name: CellTasker
Version: 0.2.4
Summary: CellTasker希望提供一个高效的任务调度和管理系统。
Home-page: https://gitee.com/colorthoro/cellular
Author: colorthoro
Author-email: dream.0112@qq.com
License: MIT
Requires-Python: >=3.1
License-File: LICENSE
